distutils-precedence.pth
_distutils_hack/__init__.py
_distutils_hack/override.py
pkg_resources/__init__.py
pkg_resources/api_tests.txt
pkg_resources/py.typed
pkg_resources/tests/__init__.py
pkg_resources/tests/test_find_distributions.py
pkg_resources/tests/test_integration_zope_interface.py
pkg_resources/tests/test_markers.py
pkg_resources/tests/test_pkg_resources.py
pkg_resources/tests/test_resources.py
pkg_resources/tests/test_working_set.py
pkg_resources/tests/data/my-test-package-source/setup.cfg
pkg_resources/tests/data/my-test-package-source/setup.py
pkg_resources/tests/data/my-test-package-zip/my-test-package.zip
pkg_resources/tests/data/my-test-package_unpacked-egg/my_test_package-1.0-py3.7.egg/EGG-INFO/PKG-INFO
pkg_resources/tests/data/my-test-package_unpacked-egg/my_test_package-1.0-py3.7.egg/EGG-INFO/SOURCES.txt
pkg_resources/tests/data/my-test-package_unpacked-egg/my_test_package-1.0-py3.7.egg/EGG-INFO/dependency_links.txt
pkg_resources/tests/data/my-test-package_unpacked-egg/my_test_package-1.0-py3.7.egg/EGG-INFO/top_level.txt
pkg_resources/tests/data/my-test-package_unpacked-egg/my_test_package-1.0-py3.7.egg/EGG-INFO/zip-safe
pkg_resources/tests/data/my-test-package_zipped-egg/my_test_package-1.0-py3.7.egg
setuptools/__init__.py
setuptools/_core_metadata.py
setuptools/_entry_points.py
setuptools/_imp.py
setuptools/_importlib.py
setuptools/_itertools.py
setuptools/_normalization.py
setuptools/_path.py
setuptools/_reqs.py
setuptools/_shutil.py
setuptools/archive_util.py
setuptools/build_meta.py
setuptools/cli-32.exe
setuptools/cli-64.exe
setuptools/cli-arm64.exe
setuptools/cli.exe
setuptools/depends.py
setuptools/discovery.py
setuptools/dist.py
setuptools/errors.py
setuptools/extension.py
setuptools/glob.py
setuptools/gui-32.exe
setuptools/gui-64.exe
setuptools/gui-arm64.exe
setuptools/gui.exe
setuptools/installer.py
setuptools/launch.py
setuptools/logging.py
setuptools/modified.py
setuptools/monkey.py
setuptools/msvc.py
setuptools/namespaces.py
setuptools/package_index.py
setuptools/sandbox.py
setuptools/script (dev).tmpl
setuptools/script.tmpl
setuptools/unicode_utils.py
setuptools/version.py
setuptools/warnings.py
setuptools/wheel.py
setuptools/windows_support.py
setuptools/_distutils/__init__.py
setuptools/_distutils/_log.py
setuptools/_distutils/_macos_compat.py
setuptools/_distutils/_modified.py
setuptools/_distutils/_msvccompiler.py
setuptools/_distutils/archive_util.py
setuptools/_distutils/ccompiler.py
setuptools/_distutils/cmd.py
setuptools/_distutils/core.py
setuptools/_vendor/platformdirs-4.2.2.dist-info/licenses/LICENSE
setuptools-75.4.0.dist-info/LICENSE
setuptools-75.4.0.dist-info/METADATA
setuptools-75.4.0.dist-info/WHEEL
setuptools-75.4.0.dist-info/entry_points.txt
setuptools-75.4.0.dist-info/top_level.txt
setuptools/_vendor/autocommand-2.2.2.dist-info/INSTALLER
setuptools/_vendor/autocommand-2.2.2.dist-info/LICENSE
setuptools/_vendor/autocommand-2.2.2.dist-info/METADATA
setuptools/_vendor/autocommand-2.2.2.dist-info/RECORD
setuptools/_vendor/autocommand-2.2.2.dist-info/WHEEL
setuptools/_vendor/autocommand-2.2.2.dist-info/top_level.txt
setuptools/_vendor/backports.tarfile-1.2.0.dist-info/INSTALLER
setuptools/_vendor/backports.tarfile-1.2.0.dist-info/LICENSE
setuptools/_vendor/backports.tarfile-1.2.0.dist-info/METADATA
setuptools/_vendor/backports.tarfile-1.2.0.dist-info/RECORD
setuptools/_vendor/backports.tarfile-1.2.0.dist-info/REQUESTED
setuptools/_vendor/backports.tarfile-1.2.0.dist-info/WHEEL
setuptools/_vendor/backports.tarfile-1.2.0.dist-info/top_level.txt
setuptools/_vendor/importlib_metadata-8.0.0.dist-info/INSTALLER
setuptools/_vendor/importlib_metadata-8.0.0.dist-info/LICENSE
setuptools/_vendor/importlib_metadata-8.0.0.dist-info/METADATA
setuptools/_vendor/importlib_metadata-8.0.0.dist-info/RECORD
setuptools/_vendor/importlib_metadata-8.0.0.dist-info/REQUESTED
setuptools/_vendor/importlib_metadata-8.0.0.dist-info/WHEEL
setuptools/_vendor/importlib_metadata-8.0.0.dist-info/top_level.txt
setuptools/_vendor/inflect-7.3.1.dist-info/INSTALLER
setuptools/_vendor/inflect-7.3.1.dist-info/LICENSE
setuptools/_vendor/inflect-7.3.1.dist-info/METADATA
setuptools/_vendor/inflect-7.3.1.dist-info/RECORD
setuptools/_vendor/inflect-7.3.1.dist-info/WHEEL
setuptools/_vendor/inflect-7.3.1.dist-info/top_level.txt
setuptools/_vendor/jaraco.collections-5.1.0.dist-info/INSTALLER
setuptools/_vendor/jaraco.collections-5.1.0.dist-info/LICENSE
setuptools/_vendor/jaraco.collections-5.1.0.dist-info/METADATA
setuptools/_vendor/jaraco.collections-5.1.0.dist-info/RECORD
setuptools/_vendor/jaraco.collections-5.1.0.dist-info/REQUESTED
setuptools/_vendor/jaraco.collections-5.1.0.dist-info/WHEEL
setuptools/_vendor/jaraco.collections-5.1.0.dist-info/top_level.txt
setuptools/_vendor/jaraco.context-5.3.0.dist-info/INSTALLER
setuptools/_vendor/jaraco.context-5.3.0.dist-info/LICENSE
setuptools/_vendor/jaraco.context-5.3.0.dist-info/METADATA
setuptools/_vendor/jaraco.context-5.3.0.dist-info/RECORD
setuptools/_vendor/jaraco.context-5.3.0.dist-info/WHEEL
setuptools/_vendor/jaraco.context-5.3.0.dist-info/top_level.txt
setuptools/_vendor/jaraco.functools-4.0.1.dist-info/INSTALLER
setuptools/_vendor/jaraco.functools-4.0.1.dist-info/LICENSE
setuptools/_vendor/jaraco.functools-4.0.1.dist-info/METADATA
setuptools/_vendor/jaraco.functools-4.0.1.dist-info/RECORD
setuptools/_vendor/jaraco.functools-4.0.1.dist-info/WHEEL
setuptools/_vendor/jaraco.functools-4.0.1.dist-info/top_level.txt
setuptools/_vendor/jaraco.text-3.12.1.dist-info/INSTALLER
setuptools/_vendor/jaraco.text-3.12.1.dist-info/LICENSE
setuptools/_vendor/jaraco.text-3.12.1.dist-info/METADATA
setuptools/_vendor/jaraco.text-3.12.1.dist-info/RECORD
setuptools/_vendor/jaraco.text-3.12.1.dist-info/REQUESTED
setuptools/_vendor/jaraco.text-3.12.1.dist-info/WHEEL
setuptools/_vendor/jaraco.text-3.12.1.dist-info/top_level.txt
setuptools/_vendor/more_itertools-10.3.0.dist-info/INSTALLER
setuptools/_vendor/more_itertools-10.3.0.dist-info/LICENSE
